beyonddesk_backend/__init__.py
beyonddesk_backend/user_service_pb2.py
beyonddesk_backend/user_service_pb2_grpc.py
beyonddesk_backend/proto/user_service.proto
beyonddesk_backend-0.1.0.dist-info/METADATA
beyonddesk_backend-0.1.0.dist-info/WHEEL
beyonddesk_backend-0.1.0.dist-info/top_level.txt
beyonddesk_backend-0.1.0.dist-info/RECORD
