Metadata-Version: 2.4
Name: beyonddesk_backend
Version: 0.1.0
Summary: gRPC service definitions for BackEnd
Home-page: https://github.com/beyond-desk/grpc-service
Author: Maruthi
Author-email: maruthi@beyonddesk.com
Classifier: Programming Language :: Python :: 3
Classifier: Operating System :: OS Independent
Requires-Python: >=3.8
Requires-Dist: grpcio>=1.66.2
Requires-Dist: grpcio-tools>=1.66.2
Requires-Dist: protobuf>=5.28.2
Dynamic: author
Dynamic: author-email
Dynamic: classifier
Dynamic: description-content-type
Dynamic: home-page
Dynamic: requires-dist
Dynamic: requires-python
Dynamic: summary
